LICENSE
p115cipher/__init__.py
p115cipher/common.py
p115cipher/const.py
p115cipher/fast.py
p115cipher/normal.py
p115cipher/py.typed
p115cipher-0.0.3.dist-info/LICENSE
p115cipher-0.0.3.dist-info/METADATA
p115cipher-0.0.3.dist-info/WHEEL
p115cipher-0.0.3.dist-info/RECORD
