Metadata-Version: 2.1
Name: p115cipher
Version: 0.0.3
Summary: 115 cipher module.
Home-page: https://github.com/ChenyangGao/web-mount-packs/tree/main/python-module/p115cipher
License: MIT
Keywords: 115,webdisk,cipher
Author: ChenyangGao
Author-email: wosiwujm@gmail.com
Requires-Python: >=3.10,<4.0
Classifier: Development Status :: 5 - Production/Stable
Classifier: Intended Audience :: Developers
Classifier: License :: OSI Approved :: MIT License
Classifier: Operating System :: OS Independent
Classifier: Programming Language :: Python
Classifier: Programming Language :: Python :: 3
Classifier: Programming Language :: Python :: 3.10
Classifier: Programming Language :: Python :: 3.11
Classifier: Programming Language :: Python :: 3.12
Classifier: Programming Language :: Python :: 3 :: Only
Classifier: Topic :: Software Development
Classifier: Topic :: Software Development :: Libraries
Classifier: Topic :: Software Development :: Libraries :: Python Modules
Requires-Dist: ecdsa
Requires-Dist: lz4
Requires-Dist: pycryptodome
Requires-Dist: python-iterutils (>=0.0.7)
Project-URL: Repository, https://github.com/ChenyangGao/web-mount-packs/tree/main/python-module/p115cipher
